{
  "hash": "d39b61eb",
  "browserHash": "b7b93987",
  "optimized": {
    "react/jsx-dev-runtime": {
      "src": "../../node_modules/react/jsx-dev-runtime.js",
      "file": "react_jsx-dev-runtime.js",
      "fileHash": "590b99d9",
      "needsInterop": true
    },
    "react": {
      "src": "../../node_modules/react/index.js",
      "file": "react.js",
      "fileHash": "50eb90d7",
      "needsInterop": true
    },
    "react-dom/client": {
      "src": "../../node_modules/react-dom/client.js",
      "file": "react-dom_client.js",
      "fileHash": "427921dd",
      "needsInterop": true
    },
    "styled-components": {
      "src": "../../node_modules/styled-components/dist/styled-components.browser.esm.js",
      "file": "styled-components.js",
      "fileHash": "3e2c2445",
      "needsInterop": false
    }
  },
  "chunks": {
    "chunk-UPDK7Z2H": {
      "file": "chunk-UPDK7Z2H.js"
    }
  }
}